cdkhelpers/hello.py
mgivney.cdkhelpers-0.1.0.dist-info/METADATA
mgivney.cdkhelpers-0.1.0.dist-info/WHEEL
mgivney.cdkhelpers-0.1.0.dist-info/top_level.txt
mgivney.cdkhelpers-0.1.0.dist-info/RECORD
