Metadata-Version: 2.1
Name: mgivney.cdkhelpers
Version: 0.1.0
Summary: CDK helpers and custom resources with sensible defaults
Home-page: UNKNOWN
Author: Matt Givney
Author-email: matt@givney.com
License: UNKNOWN
Keywords: sherwood,aws,cloudformation,cdk
Platform: UNKNOWN
Classifier: Development Status :: 3 - Alpha
Classifier: Intended Audience :: Developers
Classifier: Natural Language :: English
Classifier: Operating System :: OS Independent
Classifier: Framework :: AWS CDK
Requires-Python: >=3.7
Requires-Dist: aws-cdk.core (~=1.75.0)
Requires-Dist: aws-cdk.aws-ecs (~=1.75.0)
Requires-Dist: aws-cdk.aws-autoscaling (~=1.75.0)
Requires-Dist: aws-cdk.aws-elasticloadbalancing (~=1.75.0)
Requires-Dist: aws-cdk.aws-elasticsearch (~=1.75.0)
Requires-Dist: aws-cdk.aws-kms (~=1.75.0)
Requires-Dist: aws-cdk.aws-sqs (~=1.75.0)
Requires-Dist: aws-cdk.aws-sns (~=1.75.0)
Requires-Dist: aws-cdk.aws-s3 (~=1.75.0)
Requires-Dist: aws-cdk.aws-dynamodb (~=1.75.0)
Requires-Dist: aws-cdk.aws-ecr (~=1.75.0)
Requires-Dist: aws-cdk.aws-lambda (~=1.75.0)
Requires-Dist: aws-cdk.aws-cognito (~=1.75.0)
Requires-Dist: aws-cdk.aws-rds (~=1.75.0)
Requires-Dist: aws-cdk.aws-iam (~=1.75.0)
Requires-Dist: aws-cdk.aws-ses (~=1.75.0)
Requires-Dist: aws-cdk.aws-cloudwatch (~=1.75.0)
Requires-Dist: aws-cdk.aws-logs (~=1.75.0)
Requires-Dist: aws-cdk.aws-route53 (~=1.75.0)
Requires-Dist: aws-cdk.aws-ssm (~=1.75.0)
Requires-Dist: aws-cdk.aws-athena (~=1.75.0)
Requires-Dist: aws-cdk.aws-secretsmanager (~=1.75.0)
